sqlvalidator/__init__.py
sqlvalidator/file_formatter.py
sqlvalidator/file_handler.py
sqlvalidator/main.py
sqlvalidator/sql_formatter.py
sqlvalidator/sql_validator.py
sqlvalidator/grammar/__init__.py
sqlvalidator/grammar/lexer.py
sqlvalidator/grammar/sql.py
sqlvalidator/grammar/tokeniser.py
sqlvalidator-0.0.19.dist-info/LICENSE
sqlvalidator-0.0.19.dist-info/METADATA
sqlvalidator-0.0.19.dist-info/WHEEL
sqlvalidator-0.0.19.dist-info/entry_points.txt
sqlvalidator-0.0.19.dist-info/top_level.txt
sqlvalidator-0.0.19.dist-info/RECORD
