Metadata-Version: 2.1
Name: sqlvalidator
Version: 0.0.19
Summary: SQL queries formatting, syntactic and semantic validation
Home-page: https://github.com/David-Wobrock/sqlvalidator
Author: David Wobrock
Author-email: david.wobrock@gmail.com
License: MIT
Keywords: python sql format formatter formatting validation validator validate automation
Platform: UNKNOWN
Classifier: Development Status :: 3 - Alpha
Classifier: Intended Audience :: Developers
Classifier: Programming Language :: Python
Classifier: Programming Language :: Python :: 3
Classifier: Programming Language :: Python :: 3.7
Classifier: Programming Language :: Python :: 3.8
Classifier: Programming Language :: Python :: 3.9
Provides-Extra: test
Requires-Dist: pytest (==6.2.4) ; extra == 'test'
